tensorflow_docs/__init__.py
tensorflow_docs/api_generator/__init__.py
tensorflow_docs/api_generator/config.py
tensorflow_docs/api_generator/doc_controls.py
tensorflow_docs/api_generator/doc_controls_test.py
tensorflow_docs/api_generator/doc_generator_visitor.py
tensorflow_docs/api_generator/doc_generator_visitor_test.py
tensorflow_docs/api_generator/generate_lib.py
tensorflow_docs/api_generator/generate_lib_test.py
tensorflow_docs/api_generator/get_source.py
tensorflow_docs/api_generator/obj_type.py
tensorflow_docs/api_generator/parser.py
tensorflow_docs/api_generator/parser_test.py
tensorflow_docs/api_generator/public_api.py
tensorflow_docs/api_generator/public_api_test.py
tensorflow_docs/api_generator/reference_resolver.py
tensorflow_docs/api_generator/reference_resolver_test.py
tensorflow_docs/api_generator/signature.py
tensorflow_docs/api_generator/signature_test.py
tensorflow_docs/api_generator/toc.py
tensorflow_docs/api_generator/toc_processing.py
tensorflow_docs/api_generator/toc_processing_test.py
tensorflow_docs/api_generator/toc_test.py
tensorflow_docs/api_generator/traverse.py
tensorflow_docs/api_generator/traverse_test.py
tensorflow_docs/api_generator/utils.py
tensorflow_docs/api_generator/compat_test/__init__.py
tensorflow_docs/api_generator/compat_test/estimator.py
tensorflow_docs/api_generator/gen_java/__init__.py
tensorflow_docs/api_generator/gen_java/run-javadoc-for-tf.sh
tensorflow_docs/api_generator/gen_java/templates/class.cs
tensorflow_docs/api_generator/gen_java/templates/classes.cs
tensorflow_docs/api_generator/gen_java/templates/head_tag.cs
tensorflow_docs/api_generator/gen_java/templates/header.cs
tensorflow_docs/api_generator/gen_java/templates/left-nav-android.cs
tensorflow_docs/api_generator/gen_java/templates/macros.cs
tensorflow_docs/api_generator/gen_java/templates/navtree_data.cs
tensorflow_docs/api_generator/gen_java/templates/package-descr.cs
tensorflow_docs/api_generator/gen_java/templates/package-list.cs
tensorflow_docs-2025.2.19.33219.dist-info/AUTHORS
tensorflow_docs-2025.2.19.33219.dist-info/LICENSE
tensorflow_docs-2025.2.19.33219.dist-info/METADATA
tensorflow_docs-2025.2.19.33219.dist-info/WHEEL
tensorflow_docs-2025.2.19.33219.dist-info/top_level.txt
tensorflow_docs-2025.2.19.33219.dist-info/RECORD
