Metadata-Version: 2.2
Name: tensorflow-docs
Version: 2025.2.19.33219
Summary: tensorflow_docs is a package for generating python api-reference docs.
Home-page: http://github.com/tensorflow/docs
Download-URL: https://github.com/tensorflow/docs/tags
Author: Google Inc.
Author-email: packages@tensorflow.org
License: Apache 2.0
Keywords: tensorflow api reference
Classifier: Development Status :: 4 - Beta
Classifier: Intended Audience :: Developers
Classifier: License :: OSI Approved :: Apache Software License
Classifier: Topic :: Scientific/Engineering :: Artificial Intelligence
Requires-Python: >=3.9
License-File: LICENSE
License-File: AUTHORS
Requires-Dist: astor
Requires-Dist: absl-py
Requires-Dist: jinja2
Requires-Dist: nbformat
Requires-Dist: protobuf>=3.12
Requires-Dist: pyyaml
Provides-Extra: vis
Requires-Dist: numpy; extra == "vis"
Requires-Dist: PILLOW; extra == "vis"
Requires-Dist: webp; extra == "vis"
Dynamic: author
Dynamic: author-email
Dynamic: classifier
Dynamic: download-url
Dynamic: home-page
Dynamic: keywords
Dynamic: license
Dynamic: provides-extra
Dynamic: requires-dist
Dynamic: requires-python
Dynamic: summary
